baobab/__init__.py
baobab/generate.py
baobab/modify_existing.py
baobab/to_hdf5.py
baobab/bnn_priors/__init__.py
baobab/bnn_priors/base_bnn_prior.py
baobab/bnn_priors/base_cosmo_bnn_prior.py
baobab/bnn_priors/cov_bnn_prior.py
baobab/bnn_priors/diagonal_bnn_prior.py
baobab/bnn_priors/diagonal_cosmo_bnn_prior.py
baobab/bnn_priors/empirical_bnn_prior.py
baobab/bnn_priors/k_correction.py
baobab/bnn_priors/kinematics_models.py
baobab/bnn_priors/parameter_models.py
baobab/configs/__init__.py
baobab/configs/gamma_cov_config.py
baobab/configs/gamma_diagonal_config.py
baobab/configs/gamma_empirical_config.py
baobab/configs/parser.py
baobab/configs/tdlmc_cov_config.py
baobab/configs/tdlmc_diagonal_config.py
baobab/configs/tdlmc_diagonal_cosmo_config.py
baobab/configs/tdlmc_empirical_config.py
baobab/data_augmentation/__init__.py
baobab/data_augmentation/noise_lenstronomy.py
baobab/data_augmentation/noise_tf.py
baobab/data_augmentation/noise_torch.py
baobab/distributions/__init__.py
baobab/distributions/distributions.py
baobab/in_data/__init__.py
baobab/in_data/psf_maps/psf_101.fits
baobab/in_data/psf_maps/psf_102.fits
baobab/in_data/psf_maps/psf_103.fits
baobab/in_data/psf_maps/psf_104.fits
baobab/in_data/psf_maps/psf_105.fits
baobab/in_data/psf_maps/psf_107.fits
baobab/in_data/psf_maps/psf_108.fits
baobab/in_data/psf_maps/psf_109.fits
baobab/in_data/psf_maps/psf_110.fits
baobab/in_data/psf_maps/psf_111.fits
baobab/in_data/psf_maps/psf_113.fits
baobab/in_data/psf_maps/psf_114.fits
baobab/in_data/psf_maps/psf_115.fits
baobab/in_data/psf_maps/psf_116.fits
baobab/in_data/psf_maps/psf_117.fits
baobab/in_data/psf_maps/psf_118.fits
baobab/in_data/psf_maps/psf_150.fits
baobab/sim_utils/__init__.py
baobab/sim_utils/flux_utils.py
baobab/sim_utils/image_utils.py
baobab/sim_utils/kinematics_utils.py
baobab/sim_utils/metadata_utils.py
baobab/sim_utils/psf_utils.py
baobab/sim_utils/selection_utils.py
baobab/tests/__init__.py
baobab/tests/test_breakage.py
baobab/tests/test_generate.py
pybaobab-0.1.1.dist-info/LICENSE
pybaobab-0.1.1.dist-info/METADATA
pybaobab-0.1.1.dist-info/WHEEL
pybaobab-0.1.1.dist-info/entry_points.txt
pybaobab-0.1.1.dist-info/top_level.txt
pybaobab-0.1.1.dist-info/RECORD
