Metadata-Version: 2.1
Name: pybaobab
Version: 0.1.1
Summary: Data generator for hierarchically modeling strongly-lensed systems with Bayesian neural networks
Home-page: https://github.com/jiwoncpark/baobab
Author: Ji Won Park
Author-email: jiwon.christine.park@gmail.com
License: LICENSE.md
Keywords: physics
Platform: UNKNOWN
Classifier: Development Status :: 4 - Beta
Classifier: License :: OSI Approved :: BSD License
Classifier: Intended Audience :: Developers
Classifier: Intended Audience :: Science/Research
Classifier: Operating System :: OS Independent
Classifier: Programming Language :: Python
